<?xml version="1.0" encoding="UTF-8"?>
<faces-config>
    <managed-bean>
        <managed-bean-name>PILM036_APAC_COMPOSITE_ACTION</managed-bean-name>
        <managed-bean-class>com.iii.pel.forms.PILM036_APAC.PILM036_APAC_COMPOSITE_ACTION</managed-bean-class>
        <managed-bean-scope>session</managed-bean-scope>
    </managed-bean>
    
     <navigation-rule>
        <navigation-case>
            <from-outcome>PILM036_APAC_PM_IL_SUB_PLAN_GROUP</from-outcome>
            <to-view-id>/jsf/PILM036_APAC/PILM036_APAC_PM_IL_SUB_PLAN_GROUP.xhtml</to-view-id>
        </navigation-case>
        
           <navigation-case>
            <from-outcome>PILM036_APAC_PM_IL_SUB_PLAN</from-outcome>
            <to-view-id>/jsf/PILM036_APAC/PILM036_APAC_PM_IL_SUB_PLAN.xhtml</to-view-id>
        </navigation-case>
        
    </navigation-rule>
</faces-config>
